[
  {
    "ApiId": "/providers/microsoft.powerapps/apis/shared_excelonlinebusiness",
    "CdpRevision": {
      "BaseUrl": "/",
      "LastChangedTimeString": "2025-01-14T05:00:58.1220000Z",
      "RevisionNumber": 1
    },
    "ConnectedDataSourceInfoNameMapping": {
      "__PowerAppsId__": "__PowerAppsId__",
      "Địa chỉ báo cáo": "Địa chỉ báo cáo",
      "Điểm": "Điểm",
      "Ghi chú": "Ghi chú",
      "Giờ tuần tra": "Giờ tuần tra",
      "Image [image]": "Image [image]",
      "Mục tiêu": "Mục tiêu",
      "Người tuần tra": "Người tuần tra",
      "Tọa độ check-in": "Tọa độ check-in"
    },
    "DatasetName": "sites%252Fgssecurityjsc.sharepoint.com%252Cc7282422-0cd7-49e6-83f7-2872613ff8d2%252Cc6454a98-708d-4fcd-a9af-7b82d66dd3de,b%2521IiQox9cM5kmD9yhyYT_40phKRcaNcM1Pqa97gtZt096Qg4VymqORQLMzXjoAe8WZ,01D7XOVD75DZML3IK4MFIP4KSXQYYAXMBP",
    "EncodeDataset": false,
    "IsSampleData": false,
    "IsWritable": true,
    "Name": "Table4",
    "PkColumnIsAutoGenerated": false,
    "PkColumnName": "__PowerAppsId__",
    "Type": "ConnectedDataSourceInfo"
  }
]